version_lister/__init__.py
version_lister/add_version.py
version_lister-0.1.0.dist-info/LICENSE
version_lister-0.1.0.dist-info/METADATA
version_lister-0.1.0.dist-info/WHEEL
version_lister-0.1.0.dist-info/entry_points.txt
version_lister-0.1.0.dist-info/top_level.txt
version_lister-0.1.0.dist-info/RECORD
