Metadata-Version: 2.1
Name: version-lister
Version: 0.1.0
Summary: Hard pin your installed dependencies
Author-email: Azzam Zafar <azzam.zafar21@gmail.com>
Project-URL: Homepage, https://github.com/azzamzafar/version_lister
Project-URL: Bug Tracker, https://github.com/azzamzafar/version_lister/issues
Classifier: Programming Language :: Python :: 3
Classifier: License :: OSI Approved :: MIT License
Classifier: Operating System :: OS Independent
Requires-Python: >=3.7
License-File: LICENSE
